{
  "version": "6",
  "dialect": "sqlite",
  "id": "a4f1cfbe-21b4-4079-8547-608a25582865",
  "prevId": "00000000-0000-0000-0000-000000000000",
  "tables": {
    "act_materials": {
      "name": "act_materials",
      "columns": {
        "id": {
          "name": "id",
          "type": "integer",
          "primaryKey": true,
          "notNull": true,
          "autoincrement": true
        },
        "pouring_id": {
          "name": "pouring_id",
          "type": "integer",
          "primaryKey": false,
          "notNull": true,
          "autoincrement": false
        },
        "material_id": {
          "name": "material_id",
          "type": "integer",
          "primaryKey": false,
          "notNull": true,
          "autoincrement": false
        },
        "quantity": {
          "name": "quantity",
          "type": "real",
          "primaryKey": false,
          "notNull": true,
          "autoincrement": false
        }
      },
      "indexes": {},
      "foreignKeys": {
        "act_materials_pouring_id_pourings_id_fk": {
          "name": "act_materials_pouring_id_pourings_id_fk",
          "tableFrom": "act_materials",
          "tableTo": "pourings",
          "columnsFrom": [
            "pouring_id"
          ],
          "columnsTo": [
            "id"
          ],
          "onDelete": "no action",
          "onUpdate": "no action"
        },
        "act_materials_material_id_materials_id_fk": {
          "name": "act_materials_material_id_materials_id_fk",
          "tableFrom": "act_materials",
          "tableTo": "materials",
          "columnsFrom": [
            "material_id"
          ],
          "columnsTo": [
            "id"
          ],
          "onDelete": "no action",
          "onUpdate": "no action"
        }
      },
      "compositePrimaryKeys": {},
      "uniqueConstraints": {}
    },
    "act_photos": {
      "name": "act_photos",
      "columns": {
        "id": {
          "name": "id",
          "type": "integer",
          "primaryKey": true,
          "notNull": true,
          "autoincrement": true
        },
        "pouring_id": {
          "name": "pouring_id",
          "type": "integer",
          "primaryKey": false,
          "notNull": false,
          "autoincrement": false
        },
        "site_id": {
          "name": "site_id",
          "type": "integer",
          "primaryKey": false,
          "notNull": false,
          "autoincrement": false
        },
        "filename": {
          "name": "filename",
          "type": "text",
          "primaryKey": false,
          "notNull": true,
          "autoincrement": false
        },
        "caption": {
          "name": "caption",
          "type": "text",
          "primaryKey": false,
          "notNull": false,
          "autoincrement": false
        },
        "uploaded_at": {
          "name": "uploaded_at",
          "type": "text",
          "primaryKey": false,
          "notNull": true,
          "autoincrement": false,
          "default": "(datetime('now'))"
        }
      },
      "indexes": {},
      "foreignKeys": {
        "act_photos_pouring_id_pourings_id_fk": {
          "name": "act_photos_pouring_id_pourings_id_fk",
          "tableFrom": "act_photos",
          "tableTo": "pourings",
          "columnsFrom": [
            "pouring_id"
          ],
          "columnsTo": [
            "id"
          ],
          "onDelete": "no action",
          "onUpdate": "no action"
        },
        "act_photos_site_id_sites_id_fk": {
          "name": "act_photos_site_id_sites_id_fk",
          "tableFrom": "act_photos",
          "tableTo": "sites",
          "columnsFrom": [
            "site_id"
          ],
          "columnsTo": [
            "id"
          ],
          "onDelete": "no action",
          "onUpdate": "no action"
        }
      },
      "compositePrimaryKeys": {},
      "uniqueConstraints": {}
    },
    "act_workers": {
      "name": "act_workers",
      "columns": {
        "id": {
          "name": "id",
          "type": "integer",
          "primaryKey": true,
          "notNull": true,
          "autoincrement": true
        },
        "pouring_id": {
          "name": "pouring_id",
          "type": "integer",
          "primaryKey": false,
          "notNull": true,
          "autoincrement": false
        },
        "worker_id": {
          "name": "worker_id",
          "type": "integer",
          "primaryKey": false,
          "notNull": true,
          "autoincrement": false
        },
        "hours": {
          "name": "hours",
          "type": "real",
          "primaryKey": false,
          "notNull": true,
          "autoincrement": false
        },
        "rate": {
          "name": "rate",
          "type": "real",
          "primaryKey": false,
          "notNull": true,
          "autoincrement": false
        },
        "total": {
          "name": "total",
          "type": "real",
          "primaryKey": false,
          "notNull": true,
          "autoincrement": false
        }
      },
      "indexes": {},
      "foreignKeys": {
        "act_workers_pouring_id_pourings_id_fk": {
          "name": "act_workers_pouring_id_pourings_id_fk",
          "tableFrom": "act_workers",
          "tableTo": "pourings",
          "columnsFrom": [
            "pouring_id"
          ],
          "columnsTo": [
            "id"
          ],
          "onDelete": "no action",
          "onUpdate": "no action"
        },
        "act_workers_worker_id_workers_id_fk": {
          "name": "act_workers_worker_id_workers_id_fk",
          "tableFrom": "act_workers",
          "tableTo": "workers",
          "columnsFrom": [
            "worker_id"
          ],
          "columnsTo": [
            "id"
          ],
          "onDelete": "no action",
          "onUpdate": "no action"
        }
      },
      "compositePrimaryKeys": {},
      "uniqueConstraints": {}
    },
    "api_keys": {
      "name": "api_keys",
      "columns": {
        "id": {
          "name": "id",
          "type": "integer",
          "primaryKey": true,
          "notNull": true,
          "autoincrement": true
        },
        "name": {
          "name": "name",
          "type": "text",
          "primaryKey": false,
          "notNull": true,
          "autoincrement": false
        },
        "key": {
          "name": "key",
          "type": "text",
          "primaryKey": false,
          "notNull": true,
          "autoincrement": false
        },
        "active": {
          "name": "active",
          "type": "integer",
          "primaryKey": false,
          "notNull": true,
          "autoincrement": false,
          "default": true
        },
        "created_at": {
          "name": "created_at",
          "type": "text",
          "primaryKey": false,
          "notNull": true,
          "autoincrement": false,
          "default": "(datetime('now'))"
        }
      },
      "indexes": {
        "api_keys_key_unique": {
          "name": "api_keys_key_unique",
          "columns": [
            "key"
          ],
          "isUnique": true
        }
      },
      "foreignKeys": {},
      "compositePrimaryKeys": {},
      "uniqueConstraints": {}
    },
    "audit_log": {
      "name": "audit_log",
      "columns": {
        "id": {
          "name": "id",
          "type": "integer",
          "primaryKey": true,
          "notNull": true,
          "autoincrement": true
        },
        "user_id": {
          "name": "user_id",
          "type": "integer",
          "primaryKey": false,
          "notNull": false,
          "autoincrement": false
        },
        "action": {
          "name": "action",
          "type": "text",
          "primaryKey": false,
          "notNull": true,
          "autoincrement": false
        },
        "entity_type": {
          "name": "entity_type",
          "type": "text",
          "primaryKey": false,
          "notNull": true,
          "autoincrement": false
        },
        "entity_id": {
          "name": "entity_id",
          "type": "integer",
          "primaryKey": false,
          "notNull": false,
          "autoincrement": false
        },
        "changes": {
          "name": "changes",
          "type": "text",
          "primaryKey": false,
          "notNull": false,
          "autoincrement": false
        },
        "timestamp": {
          "name": "timestamp",
          "type": "text",
          "primaryKey": false,
          "notNull": true,
          "autoincrement": false,
          "default": "(datetime('now'))"
        }
      },
      "indexes": {},
      "foreignKeys": {
        "audit_log_user_id_users_id_fk": {
          "name": "audit_log_user_id_users_id_fk",
          "tableFrom": "audit_log",
          "tableTo": "users",
          "columnsFrom": [
            "user_id"
          ],
          "columnsTo": [
            "id"
          ],
          "onDelete": "no action",
          "onUpdate": "no action"
        }
      },
      "compositePrimaryKeys": {},
      "uniqueConstraints": {}
    },
    "clients": {
      "name": "clients",
      "columns": {
        "id": {
          "name": "id",
          "type": "integer",
          "primaryKey": true,
          "notNull": true,
          "autoincrement": true
        },
        "name": {
          "name": "name",
          "type": "text",
          "primaryKey": false,
          "notNull": true,
          "autoincrement": false
        },
        "company_name": {
          "name": "company_name",
          "type": "text",
          "primaryKey": false,
          "notNull": false,
          "autoincrement": false
        },
        "eik": {
          "name": "eik",
          "type": "text",
          "primaryKey": false,
          "notNull": false,
          "autoincrement": false
        },
        "vat_number": {
          "name": "vat_number",
          "type": "text",
          "primaryKey": false,
          "notNull": false,
          "autoincrement": false
        },
        "address": {
          "name": "address",
          "type": "text",
          "primaryKey": false,
          "notNull": false,
          "autoincrement": false
        },
        "phone": {
          "name": "phone",
          "type": "text",
          "primaryKey": false,
          "notNull": false,
          "autoincrement": false
        },
        "email": {
          "name": "email",
          "type": "text",
          "primaryKey": false,
          "notNull": false,
          "autoincrement": false
        },
        "notes": {
          "name": "notes",
          "type": "text",
          "primaryKey": false,
          "notNull": false,
          "autoincrement": false
        },
        "created_at": {
          "name": "created_at",
          "type": "text",
          "primaryKey": false,
          "notNull": true,
          "autoincrement": false,
          "default": "(datetime('now'))"
        },
        "updated_at": {
          "name": "updated_at",
          "type": "text",
          "primaryKey": false,
          "notNull": true,
          "autoincrement": false,
          "default": "(datetime('now'))"
        }
      },
      "indexes": {},
      "foreignKeys": {},
      "compositePrimaryKeys": {},
      "uniqueConstraints": {}
    },
    "concrete_types": {
      "name": "concrete_types",
      "columns": {
        "id": {
          "name": "id",
          "type": "integer",
          "primaryKey": true,
          "notNull": true,
          "autoincrement": true
        },
        "name": {
          "name": "name",
          "type": "text",
          "primaryKey": false,
          "notNull": true,
          "autoincrement": false
        },
        "class_name": {
          "name": "class_name",
          "type": "text",
          "primaryKey": false,
          "notNull": false,
          "autoincrement": false
        },
        "price_per_m3": {
          "name": "price_per_m3",
          "type": "real",
          "primaryKey": false,
          "notNull": true,
          "autoincrement": false
        },
        "description": {
          "name": "description",
          "type": "text",
          "primaryKey": false,
          "notNull": false,
          "autoincrement": false
        },
        "active": {
          "name": "active",
          "type": "integer",
          "primaryKey": false,
          "notNull": true,
          "autoincrement": false,
          "default": true
        }
      },
      "indexes": {},
      "foreignKeys": {},
      "compositePrimaryKeys": {},
      "uniqueConstraints": {}
    },
    "invoice_items": {
      "name": "invoice_items",
      "columns": {
        "id": {
          "name": "id",
          "type": "integer",
          "primaryKey": true,
          "notNull": true,
          "autoincrement": true
        },
        "invoice_id": {
          "name": "invoice_id",
          "type": "integer",
          "primaryKey": false,
          "notNull": true,
          "autoincrement": false
        },
        "description": {
          "name": "description",
          "type": "text",
          "primaryKey": false,
          "notNull": true,
          "autoincrement": false
        },
        "unit": {
          "name": "unit",
          "type": "text",
          "primaryKey": false,
          "notNull": true,
          "autoincrement": false,
          "default": "'бр.'"
        },
        "quantity": {
          "name": "quantity",
          "type": "real",
          "primaryKey": false,
          "notNull": true,
          "autoincrement": false,
          "default": 1
        },
        "price": {
          "name": "price",
          "type": "real",
          "primaryKey": false,
          "notNull": true,
          "autoincrement": false
        },
        "total": {
          "name": "total",
          "type": "real",
          "primaryKey": false,
          "notNull": true,
          "autoincrement": false
        }
      },
      "indexes": {},
      "foreignKeys": {
        "invoice_items_invoice_id_invoices_id_fk": {
          "name": "invoice_items_invoice_id_invoices_id_fk",
          "tableFrom": "invoice_items",
          "tableTo": "invoices",
          "columnsFrom": [
            "invoice_id"
          ],
          "columnsTo": [
            "id"
          ],
          "onDelete": "no action",
          "onUpdate": "no action"
        }
      },
      "compositePrimaryKeys": {},
      "uniqueConstraints": {}
    },
    "invoices": {
      "name": "invoices",
      "columns": {
        "id": {
          "name": "id",
          "type": "integer",
          "primaryKey": true,
          "notNull": true,
          "autoincrement": true
        },
        "client_id": {
          "name": "client_id",
          "type": "integer",
          "primaryKey": false,
          "notNull": true,
          "autoincrement": false
        },
        "number": {
          "name": "number",
          "type": "text",
          "primaryKey": false,
          "notNull": true,
          "autoincrement": false
        },
        "date": {
          "name": "date",
          "type": "text",
          "primaryKey": false,
          "notNull": true,
          "autoincrement": false
        },
        "due_date": {
          "name": "due_date",
          "type": "text",
          "primaryKey": false,
          "notNull": true,
          "autoincrement": false
        },
        "total": {
          "name": "total",
          "type": "real",
          "primaryKey": false,
          "notNull": true,
          "autoincrement": false,
          "default": 0
        },
        "vat_rate": {
          "name": "vat_rate",
          "type": "real",
          "primaryKey": false,
          "notNull": true,
          "autoincrement": false,
          "default": 20
        },
        "vat_amount": {
          "name": "vat_amount",
          "type": "real",
          "primaryKey": false,
          "notNull": true,
          "autoincrement": false,
          "default": 0
        },
        "status": {
          "name": "status",
          "type": "text",
          "primaryKey": false,
          "notNull": true,
          "autoincrement": false,
          "default": "'draft'"
        },
        "type": {
          "name": "type",
          "type": "text",
          "primaryKey": false,
          "notNull": true,
          "autoincrement": false,
          "default": "'invoice'"
        },
        "pdf_path": {
          "name": "pdf_path",
          "type": "text",
          "primaryKey": false,
          "notNull": false,
          "autoincrement": false
        },
        "notes": {
          "name": "notes",
          "type": "text",
          "primaryKey": false,
          "notNull": false,
          "autoincrement": false
        }
      },
      "indexes": {},
      "foreignKeys": {
        "invoices_client_id_clients_id_fk": {
          "name": "invoices_client_id_clients_id_fk",
          "tableFrom": "invoices",
          "tableTo": "clients",
          "columnsFrom": [
            "client_id"
          ],
          "columnsTo": [
            "id"
          ],
          "onDelete": "no action",
          "onUpdate": "no action"
        }
      },
      "compositePrimaryKeys": {},
      "uniqueConstraints": {}
    },
    "machine_maintenance": {
      "name": "machine_maintenance",
      "columns": {
        "id": {
          "name": "id",
          "type": "integer",
          "primaryKey": true,
          "notNull": true,
          "autoincrement": true
        },
        "machine_id": {
          "name": "machine_id",
          "type": "integer",
          "primaryKey": false,
          "notNull": true,
          "autoincrement": false
        },
        "date": {
          "name": "date",
          "type": "text",
          "primaryKey": false,
          "notNull": true,
          "autoincrement": false
        },
        "type": {
          "name": "type",
          "type": "text",
          "primaryKey": false,
          "notNull": true,
          "autoincrement": false
        },
        "description": {
          "name": "description",
          "type": "text",
          "primaryKey": false,
          "notNull": false,
          "autoincrement": false
        },
        "cost": {
          "name": "cost",
          "type": "real",
          "primaryKey": false,
          "notNull": false,
          "autoincrement": false,
          "default": 0
        },
        "next_date": {
          "name": "next_date",
          "type": "text",
          "primaryKey": false,
          "notNull": false,
          "autoincrement": false
        },
        "notes": {
          "name": "notes",
          "type": "text",
          "primaryKey": false,
          "notNull": false,
          "autoincrement": false
        }
      },
      "indexes": {},
      "foreignKeys": {
        "machine_maintenance_machine_id_machines_id_fk": {
          "name": "machine_maintenance_machine_id_machines_id_fk",
          "tableFrom": "machine_maintenance",
          "tableTo": "machines",
          "columnsFrom": [
            "machine_id"
          ],
          "columnsTo": [
            "id"
          ],
          "onDelete": "no action",
          "onUpdate": "no action"
        }
      },
      "compositePrimaryKeys": {},
      "uniqueConstraints": {}
    },
    "machines": {
      "name": "machines",
      "columns": {
        "id": {
          "name": "id",
          "type": "integer",
          "primaryKey": true,
          "notNull": true,
          "autoincrement": true
        },
        "name": {
          "name": "name",
          "type": "text",
          "primaryKey": false,
          "notNull": true,
          "autoincrement": false
        },
        "type": {
          "name": "type",
          "type": "text",
          "primaryKey": false,
          "notNull": true,
          "autoincrement": false
        },
        "plate_number": {
          "name": "plate_number",
          "type": "text",
          "primaryKey": false,
          "notNull": false,
          "autoincrement": false
        },
        "fuel_type": {
          "name": "fuel_type",
          "type": "text",
          "primaryKey": false,
          "notNull": false,
          "autoincrement": false
        },
        "status": {
          "name": "status",
          "type": "text",
          "primaryKey": false,
          "notNull": true,
          "autoincrement": false,
          "default": "'available'"
        },
        "location": {
          "name": "location",
          "type": "text",
          "primaryKey": false,
          "notNull": false,
          "autoincrement": false
        },
        "last_maintenance_date": {
          "name": "last_maintenance_date",
          "type": "text",
          "primaryKey": false,
          "notNull": false,
          "autoincrement": false
        },
        "next_maintenance_date": {
          "name": "next_maintenance_date",
          "type": "text",
          "primaryKey": false,
          "notNull": false,
          "autoincrement": false
        },
        "notes": {
          "name": "notes",
          "type": "text",
          "primaryKey": false,
          "notNull": false,
          "autoincrement": false
        }
      },
      "indexes": {},
      "foreignKeys": {},
      "compositePrimaryKeys": {},
      "uniqueConstraints": {}
    },
    "material_deliveries": {
      "name": "material_deliveries",
      "columns": {
        "id": {
          "name": "id",
          "type": "integer",
          "primaryKey": true,
          "notNull": true,
          "autoincrement": true
        },
        "material_id": {
          "name": "material_id",
          "type": "integer",
          "primaryKey": false,
          "notNull": true,
          "autoincrement": false
        },
        "date": {
          "name": "date",
          "type": "text",
          "primaryKey": false,
          "notNull": true,
          "autoincrement": false
        },
        "quantity": {
          "name": "quantity",
          "type": "real",
          "primaryKey": false,
          "notNull": true,
          "autoincrement": false
        },
        "supplier": {
          "name": "supplier",
          "type": "text",
          "primaryKey": false,
          "notNull": false,
          "autoincrement": false
        },
        "price": {
          "name": "price",
          "type": "real",
          "primaryKey": false,
          "notNull": false,
          "autoincrement": false
        },
        "notes": {
          "name": "notes",
          "type": "text",
          "primaryKey": false,
          "notNull": false,
          "autoincrement": false
        }
      },
      "indexes": {},
      "foreignKeys": {
        "material_deliveries_material_id_materials_id_fk": {
          "name": "material_deliveries_material_id_materials_id_fk",
          "tableFrom": "material_deliveries",
          "tableTo": "materials",
          "columnsFrom": [
            "material_id"
          ],
          "columnsTo": [
            "id"
          ],
          "onDelete": "no action",
          "onUpdate": "no action"
        }
      },
      "compositePrimaryKeys": {},
      "uniqueConstraints": {}
    },
    "materials": {
      "name": "materials",
      "columns": {
        "id": {
          "name": "id",
          "type": "integer",
          "primaryKey": true,
          "notNull": true,
          "autoincrement": true
        },
        "name": {
          "name": "name",
          "type": "text",
          "primaryKey": false,
          "notNull": true,
          "autoincrement": false
        },
        "unit": {
          "name": "unit",
          "type": "text",
          "primaryKey": false,
          "notNull": true,
          "autoincrement": false
        },
        "quantity": {
          "name": "quantity",
          "type": "real",
          "primaryKey": false,
          "notNull": true,
          "autoincrement": false,
          "default": 0
        },
        "min_threshold": {
          "name": "min_threshold",
          "type": "real",
          "primaryKey": false,
          "notNull": false,
          "autoincrement": false,
          "default": 0
        },
        "price_per_unit": {
          "name": "price_per_unit",
          "type": "real",
          "primaryKey": false,
          "notNull": false,
          "autoincrement": false
        },
        "notes": {
          "name": "notes",
          "type": "text",
          "primaryKey": false,
          "notNull": false,
          "autoincrement": false
        }
      },
      "indexes": {},
      "foreignKeys": {},
      "compositePrimaryKeys": {},
      "uniqueConstraints": {}
    },
    "offer_items": {
      "name": "offer_items",
      "columns": {
        "id": {
          "name": "id",
          "type": "integer",
          "primaryKey": true,
          "notNull": true,
          "autoincrement": true
        },
        "offer_id": {
          "name": "offer_id",
          "type": "integer",
          "primaryKey": false,
          "notNull": true,
          "autoincrement": false
        },
        "concrete_type_id": {
          "name": "concrete_type_id",
          "type": "integer",
          "primaryKey": false,
          "notNull": false,
          "autoincrement": false
        },
        "quantity_m3": {
          "name": "quantity_m3",
          "type": "real",
          "primaryKey": false,
          "notNull": true,
          "autoincrement": false
        },
        "price_per_m3": {
          "name": "price_per_m3",
          "type": "real",
          "primaryKey": false,
          "notNull": true,
          "autoincrement": false
        },
        "transport_cost": {
          "name": "transport_cost",
          "type": "real",
          "primaryKey": false,
          "notNull": false,
          "autoincrement": false,
          "default": 0
        },
        "pump_cost": {
          "name": "pump_cost",
          "type": "real",
          "primaryKey": false,
          "notNull": false,
          "autoincrement": false,
          "default": 0
        },
        "total": {
          "name": "total",
          "type": "real",
          "primaryKey": false,
          "notNull": true,
          "autoincrement": false
        }
      },
      "indexes": {},
      "foreignKeys": {
        "offer_items_offer_id_offers_id_fk": {
          "name": "offer_items_offer_id_offers_id_fk",
          "tableFrom": "offer_items",
          "tableTo": "offers",
          "columnsFrom": [
            "offer_id"
          ],
          "columnsTo": [
            "id"
          ],
          "onDelete": "no action",
          "onUpdate": "no action"
        },
        "offer_items_concrete_type_id_concrete_types_id_fk": {
          "name": "offer_items_concrete_type_id_concrete_types_id_fk",
          "tableFrom": "offer_items",
          "tableTo": "concrete_types",
          "columnsFrom": [
            "concrete_type_id"
          ],
          "columnsTo": [
            "id"
          ],
          "onDelete": "no action",
          "onUpdate": "no action"
        }
      },
      "compositePrimaryKeys": {},
      "uniqueConstraints": {}
    },
    "offers": {
      "name": "offers",
      "columns": {
        "id": {
          "name": "id",
          "type": "integer",
          "primaryKey": true,
          "notNull": true,
          "autoincrement": true
        },
        "client_id": {
          "name": "client_id",
          "type": "integer",
          "primaryKey": false,
          "notNull": true,
          "autoincrement": false
        },
        "site_id": {
          "name": "site_id",
          "type": "integer",
          "primaryKey": false,
          "notNull": false,
          "autoincrement": false
        },
        "number": {
          "name": "number",
          "type": "text",
          "primaryKey": false,
          "notNull": true,
          "autoincrement": false
        },
        "date": {
          "name": "date",
          "type": "text",
          "primaryKey": false,
          "notNull": true,
          "autoincrement": false
        },
        "valid_until": {
          "name": "valid_until",
          "type": "text",
          "primaryKey": false,
          "notNull": false,
          "autoincrement": false
        },
        "total": {
          "name": "total",
          "type": "real",
          "primaryKey": false,
          "notNull": true,
          "autoincrement": false,
          "default": 0
        },
        "status": {
          "name": "status",
          "type": "text",
          "primaryKey": false,
          "notNull": true,
          "autoincrement": false,
          "default": "'draft'"
        },
        "pdf_path": {
          "name": "pdf_path",
          "type": "text",
          "primaryKey": false,
          "notNull": false,
          "autoincrement": false
        },
        "notes": {
          "name": "notes",
          "type": "text",
          "primaryKey": false,
          "notNull": false,
          "autoincrement": false
        }
      },
      "indexes": {},
      "foreignKeys": {
        "offers_client_id_clients_id_fk": {
          "name": "offers_client_id_clients_id_fk",
          "tableFrom": "offers",
          "tableTo": "clients",
          "columnsFrom": [
            "client_id"
          ],
          "columnsTo": [
            "id"
          ],
          "onDelete": "no action",
          "onUpdate": "no action"
        },
        "offers_site_id_sites_id_fk": {
          "name": "offers_site_id_sites_id_fk",
          "tableFrom": "offers",
          "tableTo": "sites",
          "columnsFrom": [
            "site_id"
          ],
          "columnsTo": [
            "id"
          ],
          "onDelete": "no action",
          "onUpdate": "no action"
        }
      },
      "compositePrimaryKeys": {},
      "uniqueConstraints": {}
    },
    "pourings": {
      "name": "pourings",
      "columns": {
        "id": {
          "name": "id",
          "type": "integer",
          "primaryKey": true,
          "notNull": true,
          "autoincrement": true
        },
        "site_id": {
          "name": "site_id",
          "type": "integer",
          "primaryKey": false,
          "notNull": true,
          "autoincrement": false
        },
        "date": {
          "name": "date",
          "type": "text",
          "primaryKey": false,
          "notNull": true,
          "autoincrement": false
        },
        "concrete_type_id": {
          "name": "concrete_type_id",
          "type": "integer",
          "primaryKey": false,
          "notNull": false,
          "autoincrement": false
        },
        "quantity_m3": {
          "name": "quantity_m3",
          "type": "real",
          "primaryKey": false,
          "notNull": true,
          "autoincrement": false
        },
        "machine_id": {
          "name": "machine_id",
          "type": "integer",
          "primaryKey": false,
          "notNull": false,
          "autoincrement": false
        },
        "weather": {
          "name": "weather",
          "type": "text",
          "primaryKey": false,
          "notNull": false,
          "autoincrement": false
        },
        "notes": {
          "name": "notes",
          "type": "text",
          "primaryKey": false,
          "notNull": false,
          "autoincrement": false
        },
        "act_pdf_path": {
          "name": "act_pdf_path",
          "type": "text",
          "primaryKey": false,
          "notNull": false,
          "autoincrement": false
        },
        "status": {
          "name": "status",
          "type": "text",
          "primaryKey": false,
          "notNull": true,
          "autoincrement": false,
          "default": "'completed'"
        },
        "created_at": {
          "name": "created_at",
          "type": "text",
          "primaryKey": false,
          "notNull": true,
          "autoincrement": false,
          "default": "(datetime('now'))"
        }
      },
      "indexes": {},
      "foreignKeys": {
        "pourings_site_id_sites_id_fk": {
          "name": "pourings_site_id_sites_id_fk",
          "tableFrom": "pourings",
          "tableTo": "sites",
          "columnsFrom": [
            "site_id"
          ],
          "columnsTo": [
            "id"
          ],
          "onDelete": "no action",
          "onUpdate": "no action"
        },
        "pourings_concrete_type_id_concrete_types_id_fk": {
          "name": "pourings_concrete_type_id_concrete_types_id_fk",
          "tableFrom": "pourings",
          "tableTo": "concrete_types",
          "columnsFrom": [
            "concrete_type_id"
          ],
          "columnsTo": [
            "id"
          ],
          "onDelete": "no action",
          "onUpdate": "no action"
        },
        "pourings_machine_id_machines_id_fk": {
          "name": "pourings_machine_id_machines_id_fk",
          "tableFrom": "pourings",
          "tableTo": "machines",
          "columnsFrom": [
            "machine_id"
          ],
          "columnsTo": [
            "id"
          ],
          "onDelete": "no action",
          "onUpdate": "no action"
        }
      },
      "compositePrimaryKeys": {},
      "uniqueConstraints": {}
    },
    "site_calendar": {
      "name": "site_calendar",
      "columns": {
        "id": {
          "name": "id",
          "type": "integer",
          "primaryKey": true,
          "notNull": true,
          "autoincrement": true
        },
        "site_id": {
          "name": "site_id",
          "type": "integer",
          "primaryKey": false,
          "notNull": true,
          "autoincrement": false
        },
        "planned_date": {
          "name": "planned_date",
          "type": "text",
          "primaryKey": false,
          "notNull": true,
          "autoincrement": false
        },
        "concrete_type_id": {
          "name": "concrete_type_id",
          "type": "integer",
          "primaryKey": false,
          "notNull": false,
          "autoincrement": false
        },
        "estimated_m3": {
          "name": "estimated_m3",
          "type": "real",
          "primaryKey": false,
          "notNull": false,
          "autoincrement": false
        },
        "machine_id": {
          "name": "machine_id",
          "type": "integer",
          "primaryKey": false,
          "notNull": false,
          "autoincrement": false
        },
        "team_lead_id": {
          "name": "team_lead_id",
          "type": "integer",
          "primaryKey": false,
          "notNull": false,
          "autoincrement": false
        },
        "status": {
          "name": "status",
          "type": "text",
          "primaryKey": false,
          "notNull": true,
          "autoincrement": false,
          "default": "'planned'"
        },
        "notes": {
          "name": "notes",
          "type": "text",
          "primaryKey": false,
          "notNull": false,
          "autoincrement": false
        }
      },
      "indexes": {},
      "foreignKeys": {
        "site_calendar_site_id_sites_id_fk": {
          "name": "site_calendar_site_id_sites_id_fk",
          "tableFrom": "site_calendar",
          "tableTo": "sites",
          "columnsFrom": [
            "site_id"
          ],
          "columnsTo": [
            "id"
          ],
          "onDelete": "no action",
          "onUpdate": "no action"
        },
        "site_calendar_concrete_type_id_concrete_types_id_fk": {
          "name": "site_calendar_concrete_type_id_concrete_types_id_fk",
          "tableFrom": "site_calendar",
          "tableTo": "concrete_types",
          "columnsFrom": [
            "concrete_type_id"
          ],
          "columnsTo": [
            "id"
          ],
          "onDelete": "no action",
          "onUpdate": "no action"
        },
        "site_calendar_machine_id_machines_id_fk": {
          "name": "site_calendar_machine_id_machines_id_fk",
          "tableFrom": "site_calendar",
          "tableTo": "machines",
          "columnsFrom": [
            "machine_id"
          ],
          "columnsTo": [
            "id"
          ],
          "onDelete": "no action",
          "onUpdate": "no action"
        },
        "site_calendar_team_lead_id_workers_id_fk": {
          "name": "site_calendar_team_lead_id_workers_id_fk",
          "tableFrom": "site_calendar",
          "tableTo": "workers",
          "columnsFrom": [
            "team_lead_id"
          ],
          "columnsTo": [
            "id"
          ],
          "onDelete": "no action",
          "onUpdate": "no action"
        }
      },
      "compositePrimaryKeys": {},
      "uniqueConstraints": {}
    },
    "sites": {
      "name": "sites",
      "columns": {
        "id": {
          "name": "id",
          "type": "integer",
          "primaryKey": true,
          "notNull": true,
          "autoincrement": true
        },
        "client_id": {
          "name": "client_id",
          "type": "integer",
          "primaryKey": false,
          "notNull": true,
          "autoincrement": false
        },
        "name": {
          "name": "name",
          "type": "text",
          "primaryKey": false,
          "notNull": true,
          "autoincrement": false
        },
        "address": {
          "name": "address",
          "type": "text",
          "primaryKey": false,
          "notNull": true,
          "autoincrement": false
        },
        "status": {
          "name": "status",
          "type": "text",
          "primaryKey": false,
          "notNull": true,
          "autoincrement": false,
          "default": "'active'"
        },
        "start_date": {
          "name": "start_date",
          "type": "text",
          "primaryKey": false,
          "notNull": false,
          "autoincrement": false
        },
        "end_date": {
          "name": "end_date",
          "type": "text",
          "primaryKey": false,
          "notNull": false,
          "autoincrement": false
        },
        "notes": {
          "name": "notes",
          "type": "text",
          "primaryKey": false,
          "notNull": false,
          "autoincrement": false
        },
        "created_at": {
          "name": "created_at",
          "type": "text",
          "primaryKey": false,
          "notNull": true,
          "autoincrement": false,
          "default": "(datetime('now'))"
        },
        "updated_at": {
          "name": "updated_at",
          "type": "text",
          "primaryKey": false,
          "notNull": true,
          "autoincrement": false,
          "default": "(datetime('now'))"
        }
      },
      "indexes": {},
      "foreignKeys": {
        "sites_client_id_clients_id_fk": {
          "name": "sites_client_id_clients_id_fk",
          "tableFrom": "sites",
          "tableTo": "clients",
          "columnsFrom": [
            "client_id"
          ],
          "columnsTo": [
            "id"
          ],
          "onDelete": "no action",
          "onUpdate": "no action"
        }
      },
      "compositePrimaryKeys": {},
      "uniqueConstraints": {}
    },
    "templates": {
      "name": "templates",
      "columns": {
        "id": {
          "name": "id",
          "type": "integer",
          "primaryKey": true,
          "notNull": true,
          "autoincrement": true
        },
        "name": {
          "name": "name",
          "type": "text",
          "primaryKey": false,
          "notNull": true,
          "autoincrement": false
        },
        "type": {
          "name": "type",
          "type": "text",
          "primaryKey": false,
          "notNull": true,
          "autoincrement": false
        },
        "content": {
          "name": "content",
          "type": "text",
          "primaryKey": false,
          "notNull": true,
          "autoincrement": false
        },
        "updated_at": {
          "name": "updated_at",
          "type": "text",
          "primaryKey": false,
          "notNull": true,
          "autoincrement": false,
          "default": "(datetime('now'))"
        }
      },
      "indexes": {},
      "foreignKeys": {},
      "compositePrimaryKeys": {},
      "uniqueConstraints": {}
    },
    "users": {
      "name": "users",
      "columns": {
        "id": {
          "name": "id",
          "type": "integer",
          "primaryKey": true,
          "notNull": true,
          "autoincrement": true
        },
        "email": {
          "name": "email",
          "type": "text",
          "primaryKey": false,
          "notNull": true,
          "autoincrement": false
        },
        "password_hash": {
          "name": "password_hash",
          "type": "text",
          "primaryKey": false,
          "notNull": true,
          "autoincrement": false
        },
        "name": {
          "name": "name",
          "type": "text",
          "primaryKey": false,
          "notNull": true,
          "autoincrement": false
        },
        "role": {
          "name": "role",
          "type": "text",
          "primaryKey": false,
          "notNull": true,
          "autoincrement": false,
          "default": "'brigadir'"
        },
        "phone": {
          "name": "phone",
          "type": "text",
          "primaryKey": false,
          "notNull": false,
          "autoincrement": false
        },
        "active": {
          "name": "active",
          "type": "integer",
          "primaryKey": false,
          "notNull": true,
          "autoincrement": false,
          "default": true
        },
        "created_at": {
          "name": "created_at",
          "type": "text",
          "primaryKey": false,
          "notNull": true,
          "autoincrement": false,
          "default": "(datetime('now'))"
        },
        "updated_at": {
          "name": "updated_at",
          "type": "text",
          "primaryKey": false,
          "notNull": true,
          "autoincrement": false,
          "default": "(datetime('now'))"
        }
      },
      "indexes": {
        "users_email_unique": {
          "name": "users_email_unique",
          "columns": [
            "email"
          ],
          "isUnique": true
        }
      },
      "foreignKeys": {},
      "compositePrimaryKeys": {},
      "uniqueConstraints": {}
    },
    "worker_attendance": {
      "name": "worker_attendance",
      "columns": {
        "id": {
          "name": "id",
          "type": "integer",
          "primaryKey": true,
          "notNull": true,
          "autoincrement": true
        },
        "worker_id": {
          "name": "worker_id",
          "type": "integer",
          "primaryKey": false,
          "notNull": true,
          "autoincrement": false
        },
        "date": {
          "name": "date",
          "type": "text",
          "primaryKey": false,
          "notNull": true,
          "autoincrement": false
        },
        "site_id": {
          "name": "site_id",
          "type": "integer",
          "primaryKey": false,
          "notNull": false,
          "autoincrement": false
        },
        "hours": {
          "name": "hours",
          "type": "real",
          "primaryKey": false,
          "notNull": true,
          "autoincrement": false,
          "default": 8
        },
        "overtime": {
          "name": "overtime",
          "type": "real",
          "primaryKey": false,
          "notNull": false,
          "autoincrement": false,
          "default": 0
        },
        "advance": {
          "name": "advance",
          "type": "real",
          "primaryKey": false,
          "notNull": false,
          "autoincrement": false,
          "default": 0
        },
        "notes": {
          "name": "notes",
          "type": "text",
          "primaryKey": false,
          "notNull": false,
          "autoincrement": false
        }
      },
      "indexes": {},
      "foreignKeys": {
        "worker_attendance_worker_id_workers_id_fk": {
          "name": "worker_attendance_worker_id_workers_id_fk",
          "tableFrom": "worker_attendance",
          "tableTo": "workers",
          "columnsFrom": [
            "worker_id"
          ],
          "columnsTo": [
            "id"
          ],
          "onDelete": "no action",
          "onUpdate": "no action"
        },
        "worker_attendance_site_id_sites_id_fk": {
          "name": "worker_attendance_site_id_sites_id_fk",
          "tableFrom": "worker_attendance",
          "tableTo": "sites",
          "columnsFrom": [
            "site_id"
          ],
          "columnsTo": [
            "id"
          ],
          "onDelete": "no action",
          "onUpdate": "no action"
        }
      },
      "compositePrimaryKeys": {},
      "uniqueConstraints": {}
    },
    "workers": {
      "name": "workers",
      "columns": {
        "id": {
          "name": "id",
          "type": "integer",
          "primaryKey": true,
          "notNull": true,
          "autoincrement": true
        },
        "name": {
          "name": "name",
          "type": "text",
          "primaryKey": false,
          "notNull": true,
          "autoincrement": false
        },
        "phone": {
          "name": "phone",
          "type": "text",
          "primaryKey": false,
          "notNull": false,
          "autoincrement": false
        },
        "daily_rate": {
          "name": "daily_rate",
          "type": "real",
          "primaryKey": false,
          "notNull": true,
          "autoincrement": false
        },
        "overtime_rate": {
          "name": "overtime_rate",
          "type": "real",
          "primaryKey": false,
          "notNull": false,
          "autoincrement": false
        },
        "status": {
          "name": "status",
          "type": "text",
          "primaryKey": false,
          "notNull": true,
          "autoincrement": false,
          "default": "'active'"
        },
        "hire_date": {
          "name": "hire_date",
          "type": "text",
          "primaryKey": false,
          "notNull": false,
          "autoincrement": false
        },
        "notes": {
          "name": "notes",
          "type": "text",
          "primaryKey": false,
          "notNull": false,
          "autoincrement": false
        }
      },
      "indexes": {},
      "foreignKeys": {},
      "compositePrimaryKeys": {},
      "uniqueConstraints": {}
    }
  },
  "enums": {},
  "_meta": {
    "schemas": {},
    "tables": {},
    "columns": {}
  },
  "internal": {
    "indexes": {}
  }
}